{
  "testId": "IELTS_3_9_SPACE_2025_09_29",
  "testDate": "2025-09-29",
  "testTitle": "IELTS 3.9 — Space Systems & Mission Ops Focus — Practice Test (EN–VI)",
  "totalQuestions": 60,
  "sections": {
    "grammar": {
      "title": "Section A: Grammar & Vocabulary in Space Systems",
      "titleVi": "Phần A: Ngữ pháp & Từ vựng trong bối cảnh hệ thống vũ trụ",
      "description": "30 MCQs • Advanced mandative subjunctive, multi-clause inversion, mixed/3rd conditionals, cleft sentences, precision quantifiers, reduced relatives, domain collocations (telemetry, rendezvous, delta-v, payload integration, contingency burn)",
      "descriptionVi": "30 câu trắc nghiệm • Thức giả định mệnh lệnh nâng cao, đảo ngữ nhiều mệnh đề, điều kiện hỗn hợp/loại 3, câu chẻ, lượng từ chính xác, mệnh đề rút gọn, kết hợp từ chuyên ngành (telemetry, gặp quỹ đạo, delta-v, tích hợp tải trọng, đốt khẩn)",
      "totalQuestions": 30,
      "questions": [
        {
          "id": 1,
          "question": "The mission director insisted that the docking module ___ pressure-tested before integration.",
          "questionVi": "Giám đốc nhiệm vụ yêu cầu mô-đun ghép nối ___ kiểm tra áp suất trước khi tích hợp.",
          "options": ["be", "is", "to be", "being"],
          "optionsVi": ["được", "đang", "để được", "đang được"],
          "correct": 0
        },
        {
          "id": 2,
          "question": "Not until telemetry flagged the micro-leak ___ the spacecraft entered contingency burn mode.",
          "questionVi": "Mãi đến khi số liệu telemetry báo rò rỉ nhỏ ___ tàu vũ trụ mới vào chế độ đốt khẩn.",
          "options": ["did", "was", "had", "will"],
          "optionsVi": ["mới", "đã", "đã", "sẽ"],
          "correct": 0
        },
        {
          "id": 3,
          "question": "If the staging sequence ___ correctly, the second-stage burn would have achieved planned delta-v.",
          "questionVi": "Nếu chuỗi tách tầng ___ đúng, đốt tầng hai đã đạt delta-v theo kế hoạch.",
          "options": ["had executed", "executed", "was executing", "would execute"],
          "optionsVi": ["đã thực hiện", "đã thực hiện", "đang thực hiện", "sẽ thực hiện"],
          "correct": 0
        },
        {
          "id": 4,
          "question": "Hardly ___ the range gate opened when the target came into view on LIDAR.",
          "questionVi": "Vừa khi ___ cửa sập phạm vi mở thì mục tiêu đã vào tầm nhìn trên LIDAR.",
          "options": ["had", "was", "did", "has"],
          "optionsVi": ["vừa khi", "đã", "đã", "đã"],
          "correct": 0
        },
        {
          "id": 5,
          "question": "It is critical that the flight software ___ validated on the hardware-in-the-loop bench.",
          "questionVi": "Rất quan trọng là phần mềm bay phải ___ xác thực trên băng thử phần cứng-in-the-loop.",
          "options": ["be", "is", "to be", "being"],
          "optionsVi": ["được", "đang", "để được", "đang được"],
          "correct": 0
        },
        {
          "id": 6,
          "question": "No sooner ___ the orbital insertion burn than ground ops reported an anomalous attitude drift.",
          "questionVi": "Vừa khi ___ đốt đưa quỹ đạo thì điều hành mặt đất báo trôi phương vị bất thường.",
          "options": ["had", "we had", "did", "have"],
          "optionsVi": ["vừa khi", "chúng tôi vừa", "đã", "đã"],
          "correct": 0
        },
        {
          "id": 7,
          "question": "Were the payload heavier, the transfer orbit ___ more propellant to achieve.",
          "questionVi": "Nếu tải trọng nặng hơn, quỹ đạo chuyển tải ___ cần nhiều nhiên liệu hơn để đạt được.",
          "options": ["would require", "required", "will require", "would have required"],
          "optionsVi": ["sẽ cần", "đã cần", "sẽ cần", "đã cần"],
          "correct": 0
        },
        {
          "id": 8,
          "question": "Seldom ___ rendezvous attempts succeed on first approach without precise relative navigation.",
          "questionVi": "Hiếm khi ___ nỗ lực gặp quỹ đạo thành công lần đầu nếu không có định vị tương đối chính xác.",
          "options": ["do", "does", "have", "is"],
          "optionsVi": ["làm", "làm", "đã", "là"],
          "correct": 0
        },
        {
          "id": 9,
          "question": "By the time the beacon ___, the chaser had matched thrust vector alignment twice.",
          "questionVi": "Khi tín hiệu phát ___, tàu bắt đã khớp hướng lực đẩy hai lần.",
          "options": ["locked", "had locked", "has locked", "will lock"],
          "optionsVi": ["khóa", "đã khóa", "đã khóa", "sẽ khóa"],
          "correct": 1
        },
        {
          "id": 10,
          "question": "She briefed as though she ___ the entire payload manifest by heart.",
          "questionVi": "Cô ấy báo cáo như thể ___ thuộc lòng toàn bộ danh mục tải trọng.",
          "options": ["knew", "has known", "would know", "knows"],
          "optionsVi": ["biết", "đã biết", "sẽ biết", "biết"],
          "correct": 0
        },
        {
          "id": 11,
          "question": "Only after the AIT sign-offs ___ did the prime contractor ship the stack to the pad.",
          "questionVi": "Chỉ sau khi phê duyệt AIT ___ thì nhà thầu chính mới chuyển cấu trúc ra bệ phóng.",
          "options": ["were", "did", "was", "have"],
          "optionsVi": ["đã (số nhiều)", "mới", "đã", "đã"],
          "correct": 0
        },
        {
          "id": 12,
          "question": "There were far ___ fault indications in telemetry this window than the previous one.",
          "questionVi": "Có ___ chỉ báo lỗi trên telemetry ở cửa sổ này so với cửa sổ trước.",
          "options": ["fewer", "less", "many", "more"],
          "optionsVi": ["ít hơn (đếm được)", "ít hơn (không đếm được)", "nhiều", "nhiều hơn"],
          "correct": 0
        },
        {
          "id": 13,
          "question": "Neither the avionics lead nor the propulsion team ___ able to explain the transient spike.",
          "questionVi": "Cả trưởng avionics lẫn đội hệ thống đẩy đều không ___ giải thích được đột biến thoáng qua.",
          "options": ["was", "were", "is", "have been"],
          "optionsVi": ["đã", "đã (số nhiều)", "là", "đã"],
          "correct": 1
        },
        {
          "id": 14,
          "question": "Had the crossfeed valve been closed, the fuel imbalance ___ avoided.",
          "questionVi": "Nếu van chuyển nhiên liệu đã được đóng, mất cân bằng nhiên liệu đã ___ tránh được.",
          "options": ["would have been", "was", "will be", "has been"],
          "optionsVi": ["đã được", "đã", "sẽ được", "đã được"],
          "correct": 0
        },
        {
          "id": 15,
          "question": "The systems engineer suggested that they ___ an extra telemetry window for the rendezvous phase.",
          "questionVi": "Kỹ sư hệ thống đề nghị họ ___ một cửa sổ telemetry bổ sung cho pha gặp quỹ đạo.",
          "options": ["open", "opens", "to open", "opening"],
          "optionsVi": ["mở", "mở (ngôi 3)", "để mở", "đang mở"],
          "correct": 0
        },
        {
          "id": 16,
          "question": "Few as the margins were, ___ jeopardised the soft-capture sequence.",
          "questionVi": "Dù biên an toàn ít, ___ đã làm nguy cơ chuỗi bắt mềm.",
          "options": ["one of them", "each of them", "all of which", "several"], 
          "optionsVi": ["một trong số đó", "mỗi cái", "tất cả những cái đó", "vài cái"], 
          "correct": 2
        },
        {
          "id": 17,
          "question": "Scarcely ___ the alignment completed when a micro-meteorite debit pinged the hull.",
          "questionVi": "Vừa khi ___ căn chỉnh hoàn tất thì một va chạm vi thiên thạch nhỏ đã chạm vỏ tàu.",
          "options": ["had", "we had", "did", "have"],
          "optionsVi": ["vừa khi", "chúng tôi vừa", "đã", "đã"],
          "correct": 0
        },
        {
          "id": 18,
          "question": "The attitude control thruster should fire ___ the peak manoeuvre to avoid saturation.",
          "questionVi": "Động cơ kiểm soát phương vị nên phun ___ điểm cao thao diễn để tránh bão hoà.",
          "options": ["before", "after", "during", "without"],
          "optionsVi": ["trước", "sau", "trong", "không có"],
          "correct": 0
        },
        {
          "id": 19,
          "question": "Were the ground station offline, our telemetry buffer would quickly ___.",
          "questionVi": "Nếu trạm mặt đất bị ngoại tuyến, bộ đệm telemetry của chúng ta sẽ nhanh chóng ___.",
          "options": ["fill", "filled", "filling", "have filled"],
          "optionsVi": ["đầy", "đã đầy", "đang đầy", "đã đầy"],
          "correct": 0
        },
        {
          "id": 20,
          "question": "There is ___ time to re-plan the burn sequence before T-0; proceed with the contingency protocol.",
          "questionVi": "___ thời gian để lập lại kế hoạch chuỗi đốt trước T-0; tiến hành giao thức khẩn.",
          "options": ["little", "a few", "few", "the little"],
          "optionsVi": ["rất ít", "một vài", "ít", "rất ít (xác định)"],
          "correct": 0
        },
        {
          "id": 21,
          "question": "It was the guidance computer, not the star tracker, that ___ misaligned.",
          "questionVi": "Chính máy tính dẫn đường chứ không phải máy dò sao đã ___ lệch.",
          "options": ["was", "were", "has", "had"],
          "optionsVi": ["đã", "đã (số nhiều)", "đã", "đã"],
          "correct": 0
        },
        {
          "id": 22,
          "question": "By next window, the ops team ___ a complete comms contingency plan in place.",
          "questionVi": "Trong cửa sổ tiếp theo, đội điều hành sẽ ___ một kế hoạch dự phòng liên lạc hoàn chỉnh.",
          "options": ["will have", "have", "had", "would have"],
          "optionsVi": ["sẽ đã", "đã", "đã", "sẽ đã"],
          "correct": 0
        },
        {
          "id": 23,
          "question": "Little ___ the prime contractor foresee that the thermal soak would alter sensor bias.",
          "questionVi": "Nhà thầu chính hầu như không ___ rằng hấp thụ nhiệt sẽ thay đổi độ lệch cảm biến.",
          "options": ["did", "does", "had", "was"],
          "optionsVi": ["biết (đảo ngữ)", "biết", "đã", "đã"],
          "correct": 0
        },
        {
          "id": 24,
          "question": "No amount of attitude adjustments ___ a failed star tracker when the sensor is saturated.",
          "questionVi": "Không bao nhiêu điều chỉnh phương vị có thể ___ một máy dò sao bị lỗi khi cảm biến bão hòa.",
          "options": ["replaces", "replace", "has replaced", "replacing"],
          "optionsVi": ["thay thế được", "thay thế", "đã thay thế", "đang thay thế"],
          "correct": 0
        },
        {
          "id": 25,
          "question": "We’d rather you ___ the proximity-ops checklist than risk a collision in approach.",
          "questionVi": "Chúng tôi muốn bạn ___ danh sách kiểm tra vận hành cận tiếp hơn là mạo hiểm va chạm khi tiếp cận.",
          "options": ["run through", "ran through", "to run through", "running through"],
          "optionsVi": ["chạy qua", "đã chạy qua", "để chạy qua", "đang chạy qua"],
          "correct": 0
        },
        {
          "id": 26,
          "question": "Had it not ___ for the fuel-sensor override, the mission would have aborted.",
          "questionVi": "Nếu không ___ ghi đè cảm biến nhiên liệu, nhiệm vụ đã phải hủy bỏ.",
          "options": ["been", "be", "being", "to be"],
          "optionsVi": ["là/đã", "là", "đang là", "để là"],
          "correct": 0
        },
        {
          "id": 27,
          "question": "The more precise our delta-v budget, the ___ efficient the transfer burns become.",
          "questionVi": "Delta-v càng chính xác, các đốt chuyển tải càng ___ hiệu quả.",
          "options": ["more", "less", "fewer", "little"],
          "optionsVi": ["hơn", "ít hơn", "ít hơn (đếm được)", "ít"],
          "correct": 0
        },
        {
          "id": 28,
          "question": "Engineers capable of manual attitude correction under comms lag ___ favoured for the live console.",
          "questionVi": "Kỹ sư có khả năng chỉnh phương vị thủ công khi trễ liên lạc ___ được ưu tiên cho bảng điều khiển trực tiếp.",
          "options": ["are", "being", "who are", "which are"],
          "optionsVi": ["là", "đang", "người mà", "cái mà"],
          "correct": 0
        },
        {
          "id": 29,
          "question": "No sooner had the sealing compound cured ___ the vacuum test resumed without anomaly.",
          "questionVi": "Vừa khi hỗn hợp trám khô ___ thì thử chân không nối lại không có bất thường.",
          "options": ["than", "when", "that", "then"],
          "optionsVi": ["thì", "khi", "rằng", "rồi"],
          "correct": 0
        },
        {
          "id": 30,
          "question": "If you lose a beacon lock, keep station keeping until ___ a new solution is confirmed.",
          "questionVi": "Nếu mất khóa tín hiệu, duy trì giữ vị trí cho đến khi ___ phương án mới được xác nhận.",
          "options": ["until", "unless", "though", "despite"],
          "optionsVi": ["cho đến khi", "trừ khi", "mặc dù", "bất chấp"],
          "correct": 0
        }
      ]
    },
    "reading": {
      "title": "Section B: Reading Comprehension — Space Systems & Mission Planning",
      "titleVi": "Phần B: Đọc hiểu — Hệ thống vũ trụ & Lập kế hoạch nhiệm vụ",
      "description": "20 MCQs • Long, complex passages — multi-step causality (design → test → ops), inference, writer's stance, vocab-in-context (AIT, HIRL, rendezvous windows, contamination control)",
      "descriptionVi": "20 câu trắc nghiệm • Đoạn dài, phức tạp — nhân quả nhiều bước (thiết kế → thử → vận hành), suy luận, quan điểm tác giả, từ theo ngữ cảnh (AIT, HIRL, cửa sổ gặp, kiểm soát nhiễm bẩn)",
      "totalQuestions": 20,
      "passages": [
        {
          "id": 1,
          "title": "Passage 1 – Integrated Testing, Contamination Control and Mission Readiness",
          "titleVi": "Đoạn 1 – Thử nghiệm tích hợp, kiểm soát nhiễm bẩn và sẵn sàng nhiệm vụ",
          "content": "A medium-class spacecraft program restructured Acceptance, Integration & Test (AIT) after a near-miss: residual particulate from an improperly cleaned harness caused a sensor contamination signature that led to a false-positive proximity alarm during final approach rehearsals. The program instituted layered contamination control: cleaned harnesses in ISO Class 5 rooms, dedicated toolsets quarantined post-use, and an additional humidity-controlled bake for sensitive optics. A hardware-in-the-loop (HITL) sequence was expanded to include worst-case particulate injection tests and repeated rendezvous rehearsals with blind telemetry (to ensure ops teams relied on processed nav solutions rather than raw echoes). Over the subsequent two months, rendezvous rehearsal anomalies fell by 64% and AIT holdpoints reduced by half. However, the systems manager emphasised that the improvement hinged on three linked conditions: stricter contamination control → expanded HITL scenarios → disciplined telemetry processing in ops. When any node became lax—e.g., tools returned from quarantine without re-cleaning—false signatures reappeared and a previously removed AIT holdpoint had to be reinstated. The programme decided to codify stricter supplier contracts (cleaning SLA, traceability logs) and run quarterly cross-discipline audits. Launch readiness will be retained only if rendezvous anomaly rate remains below 3% over a 90-day rolling window and supplier traceability yields complete chain-of-custody records for 98% of harnesses.",
          "contentVi": "Một chương trình tàu vũ trụ phân loại trung bình tái cấu trúc AIT sau một sự cố suýt xảy ra: hạt dư từ dây buộc không được làm sạch đúng cách gây dấu hiệu nhiễm bẩn cảm biến dẫn tới báo động cận tiếp dương tính giả trong buổi tổng duyệt tiếp cận cuối cùng. Chương trình thiết lập kiểm soát nhiễm bẩn nhiều tầng: làm sạch dây buộc trong phòng ISO Class 5, bộ dụng cụ chuyên dụng cách ly sau khi sử dụng, và nướng điều khiển độ ẩm bổ sung cho ống kính nhạy cảm. Chuỗi HITL được mở rộng bao gồm thử nghiệm tiêm hạt tệ nhất và tổng duyệt gặp quỹ đạo lặp lại với telemetry ẩn (để đội ops dựa vào giải pháp dẫn đường đã xử lý thay vì tiếng vọng thô). Trong hai tháng tiếp theo, bất thường ở tổng duyệt gặp giảm 64% và điểm dừng AIT giảm một nửa. Tuy nhiên, quản lý hệ thống nhấn mạnh rằng cải thiện dựa trên ba điều kiện liên kết: kiểm soát nhiễm bẩn nghiêm ngặt → kịch bản HITL mở rộng → xử lý telemetry kỷ luật trong ops. Khi bất kỳ nút nào lơi lỏng—ví dụ, dụng cụ trả về từ cách ly mà không được làm sạch lại—dấu hiệu giả lại xuất hiện và một điểm dừng AIT từng loại bỏ phải tái áp dụng. Chương trình quyết định ghi vào hợp đồng nhà cung cấp chặt chẽ hơn (SLA làm sạch, nhật ký truy xuất) và chạy kiểm toán chéo định kỳ. Sẵn sàng phóng sẽ được giữ chỉ nếu tỷ lệ bất thường gặp quỹ đạo dưới 3% trong cửa sổ cuộn 90 ngày và truy xuất nguồn gốc nhà cung cấp có đầy đủ chuỗi bảo quản cho 98% dây buộc.",
          "questions": [
            {
              "id": 31,
              "question": "Primary trigger for AIT restructuring:",
              "questionVi": "Nguyên nhân chính khiến tái cấu trúc AIT:",
              "options": ["Budget overrun", "Residual particulate causing sensor contamination near-miss", "Supplier bankruptcy", "Launch delay due to weather"],
              "optionsVi": ["Vượt ngân sách", "Hạt dư gây nhiễm bẩn cảm biến suýt xảy ra sự cố", "Nhà cung cấp phá sản", "Trì hoãn phóng vì thời tiết"],
              "correct": 1
            },
            {
              "id": 32,
              "question": "Which control was NOT introduced?",
              "questionVi": "Biện pháp nào KHÔNG được đưa vào?",
              "options": ["ISO Class 5 cleaning", "Dedicated quarantined toolsets", "Humidity-controlled optical bake", "Eliminating HITL tests entirely"],
              "optionsVi": ["Làm sạch ISO Class 5", "Bộ dụng cụ cách ly", "Nướng điều khiển độ ẩm", "Loại bỏ hoàn toàn test HITL"],
              "correct": 3
            },
            {
              "id": 33,
              "question": "HITL expansion included:",
              "questionVi": "Mở rộng HITL bao gồm:",
              "options": ["Only software-in-the-loop", "Worst-case particulate injection and blind telemetry rendezvous rehearsals", "Removing telemetry processing", "Skipping rendezvous rehearsals"],
              "optionsVi": ["Chỉ phần mềm-in-the-loop", "Tiêm hạt tệ nhất và tổng duyệt gặp với telemetry ẩn", "Loại xử lý telemetry", "Bỏ tổng duyệt gặp quỹ đạo"],
              "correct": 1
            },
            {
              "id": 34,
              "question": "The linked conditions the manager mentioned are:",
              "questionVi": "Các điều kiện liên kết mà quản lý nhắc tới là:",
              "options": ["Contamination control → HITL → telemetry processing", "Faster builds → more tests → fewer audits", "Cheaper suppliers → less cleaning → more testing", "Longer schedules → fewer rehearsals → more launches"],
              "optionsVi": ["Kiểm soát nhiễm bẩn → HITL → xử lý telemetry", "Xây dựng nhanh hơn → nhiều test hơn → ít kiểm toán", "Nhà cung cấp rẻ hơn → ít làm sạch → nhiều test", "Lịch dài hơn → ít tổng duyệt → nhiều phóng"],
              "correct": 0
            },
            {
              "id": 35,
              "question": "What happened when quarantine rules were lax?",
              "questionVi": "Điều gì xảy ra khi quy tắc cách ly lơi lỏng?",
              "options": ["False signatures reappeared and an AIT holdpoint reinstated", "Everything improved", "Suppliers returned more harnesses", "Telemetry disappeared completely"],
              "optionsVi": ["Dấu hiệu giả xuất hiện lại và điểm dừng AIT được tái áp dụng", "Tất cả cải thiện", "Nhà cung cấp trả nhiều dây buộc hơn", "Telemetry biến mất hoàn toàn"],
              "correct": 0
            },
            {
              "id": 36,
              "question": "Which contract change did the programme add?",
              "questionVi": "Thay đổi hợp đồng nào chương trình bổ sung?",
              "options": ["Cleaning SLA and traceability logs", "Shorter delivery windows", "No supplier audits", "Lower cleaning standards"],
              "optionsVi": ["SLA làm sạch và nhật ký truy xuất", "Cửa sổ giao hàng ngắn hơn", "Không kiểm toán nhà cung cấp", "Tiêu chuẩn làm sạch thấp hơn"],
              "correct": 0
            },
            {
              "id": 37,
              "question": "Success criterion for retaining launch readiness:",
              "questionVi": "Tiêu chí giữ sẵn sàng phóng:",
              "options": ["Rendezvous anomaly <3% over 90 days and 98% chain-of-custody for harnesses", "Zero anomalies immediately", "More harnesses than before", "No supplier contracts"],
              "optionsVi": ["Bất thường gặp <3% trong 90 ngày và 98% chuỗi bảo quản", "Không có bất thường ngay lập tức", "Nhiều dây buộc hơn trước", "Không hợp đồng nhà cung cấp"], 
              "correct": 0
            },
            {
              "id": 38,
              "question": "Inference: blind telemetry rehearsals were used to ensure teams:",
              "questionVi": "Suy luận: tổng duyệt telemetry ẩn được dùng để đảm bảo đội:",
              "options": ["Relied on processed nav solutions not raw echoes", "Stopped using processed solutions", "Only trusted raw sensor data", "Ignored nav solutions"], 
              "optionsVi": ["Dựa vào giải pháp dẫn đường đã xử lý chứ không phải tiếng vọng thô", "Ngừng dùng giải pháp xử lý", "Chỉ tin dữ liệu cảm biến thô", "Bỏ qua giải pháp dẫn đường"], 
              "correct": 0
            },
            {
              "id": 39,
              "question": "Tone of passage:",
              "questionVi": "Giọng điệu đoạn văn:",
              "options": ["Technical and corrective", "Promotional", "Satirical", "Romantic"], 
              "optionsVi": ["Kỹ thuật và sửa chữa", "Quảng bá", "Châm biếm", "Lãng mạn"], 
              "correct": 0
            },
            {
              "id": 40,
              "question": "Best summary:",
              "questionVi": "Tóm tắt tốt nhất:",
              "options": ["Stricter contamination control + expanded HITL + disciplined telemetry processing cut anomalies and required supplier traceability", "Eliminate all AIT holdpoints", "Ignore supplier cleaning", "Telemetry is unnecessary"], 
              "optionsVi": ["Kiểm soát nhiễm bẩn nghiêm ngặt + mở rộng HITL + xử lý telemetry kỷ luật giảm bất thường và yêu cầu truy xuất nhà cung cấp", "Loại bỏ tất cả điểm dừng AIT", "Bỏ làm sạch nhà cung cấp", "Telemetry không cần thiết"], 
              "correct": 0
            }
          ]
        },
        {
          "id": 2,
          "title": "Passage 2 – Mission Ops: Scheduling Rendezvous Windows Under Constraints",
          "titleVi": "Đoạn 2 – Vận hành nhiệm vụ: Lên lịch cửa sổ gặp quỹ đạo trong điều kiện ràng buộc",
          "content": "Matching two spacecraft for a close-proximity operation requires a narrow rendezvous window driven by orbital mechanics, communication passes, ground-station availability, and participant fuel budgets. A mission operations team described a scheduling model that integrates predicted perturbations (e.g., atmospheric drag for low LEO altitudes, third-body effects near lunar transfers), DSN pass allocations, and constrained delta-v budgets to propose candidate windows. The model prioritises windows where the sum of station contact time and predicted manoeuvre time exceeds a threshold—ensuring redundancy for unplanned burns—while rejecting windows that would leave less than a minimum fuel reserve post-correction. In one case study, a window that met DSN availability failed once predictive drag estimates were updated: the margin for mid-course correction vanished and the team reallocated a higher-thrust burn earlier, which preserved the rendezvous but cost additional propellant and required replanning of downstream payload activities. The ops lead warned that scheduling gains depended on accurate upstream inputs: precise atmospheric models, up-to-date ephemerides, and dependable DSN schedules. The team proposed a 'grace buffer' policy—reserve 10% extra delta-v and 15% extra station contact time for complex rendezvous—and would treat launches as green only when simulated windows met buffer thresholds across a 30-day Monte Carlo ensemble.",
          "contentVi": "Ghép hai tàu vũ trụ cho thao tác cận tiếp cần một cửa sổ gặp hẹp do động lực quỹ đạo, lượt truyền thông, khả năng trạm mặt đất và ngân sách nhiên liệu của mỗi bên. Một đội vận hành nhiệm vụ mô tả mô hình lập lịch tích hợp dao động dự đoán (ví dụ, lực cản khí quyển ở độ cao LEO thấp, hiệu ứng thiên thể thứ ba gần chuyển Luna), phân bổ lượt DSN và ngân sách delta-v hạn chế để đề xuất cửa sổ ứng viên. Mô hình ưu tiên cửa sổ nơi tổng thời gian tiếp xúc trạm và thời gian thao diễn dự đoán vượt ngưỡng—đảm bảo dự phòng cho đốt ngoài kế hoạch—trong khi từ chối cửa sổ để lại dự trữ nhiên liệu tối thiểu sau khi sửa. Trong một nghiên cứu, một cửa sổ đáp ứng DSN nhưng thất bại khi ước tính lực cản khí quyển được cập nhật: biên cho sửa giữa đường biến mất và đội phải dời đốt công suất cao hơn sớm hơn, điều này giữ được cuộc gặp nhưng tốn thêm nhiên liệu và yêu cầu lập lại kế hoạch hoạt động tải trọng hạ nguồn. Trưởng ops cảnh báo lợi ích lập lịch phụ thuộc dữ liệu đầu vào trên: mô hình khí quyển chính xác, hiệu tinh lịch cập nhật và lịch DSN đáng tin. Đội đề xuất chính sách 'grace buffer'—dự trữ 10% delta-v và 15% thời gian tiếp xúc trạm cho các gặp phức tạp—và chỉ xem phóng là xanh khi cửa sổ mô phỏng thỏa ngưỡng buffer trong một ensemble Monte Carlo 30 ngày.",
          "questions": [
            {
              "id": 41,
              "question": "What factors drive the rendezvous window narrowness?",
              "questionVi": "Những yếu tố nào làm cửa sổ gặp hẹp?",
              "options": ["Only fuel budgets", "Orbital mechanics, comms passes, ground-station availability, and fuel budgets", "Crew preference", "Launch vehicle color"], 
              "optionsVi": ["Chỉ ngân sách nhiên liệu", "Động lực quỹ đạo, lượt truyền, khả năng trạm mặt đất và ngân sách nhiên liệu", "Ưa thích phi hành đoàn", "Màu phương tiện phóng"], 
              "correct": 1
            },
            {
              "id": 42,
              "question": "Model prioritises windows where:",
              "questionVi": "Mô hình ưu tiên cửa sổ nơi:",
              "options": ["Sum of station contact + manoeuvre time exceeds a threshold", "DSN is unavailable", "No fuel required", "Only one ground station is used"], 
              "optionsVi": ["Tổng thời gian tiếp xúc trạm + thời gian thao diễn vượt ngưỡng", "DSN không sẵn", "Không cần nhiên liệu", "Chỉ dùng một trạm"], 
              "correct": 0
            },
            {
              "id": 43,
              "question": "What caused the initially acceptable window to fail in the case study?",
              "questionVi": "Điều gì làm cửa sổ trước đó chấp nhận được thất bại trong nghiên cứu trường hợp?", 
              "options": ["Updated predictive drag estimates removing correction margin", "DSN doubled allocations", "Fuel budgets increased", "Ground station added more contact time"], 
              "optionsVi": ["Cập nhật ước tính lực cản khí quyển làm mất biên sửa", "DSN tăng allocations", "Ngân sách nhiên liệu tăng", "Trạm mặt đất thêm thời gian tiếp xúc"], 
              "correct": 0
            },
            {
              "id": 44,
              "question": "The team’s mitigation required:",
              "questionVi": "Biện pháp của đội đòi hỏi:", 
              "options": ["A later lower-thrust burn", "An earlier higher-thrust burn, extra propellant and replanning payload activities", "Cancel the mission", "Ignore DSN schedules"], 
              "optionsVi": ["Đốt muộn công suất thấp", "Đốt sớm công suất cao hơn, thêm nhiên liệu và lập lại kế hoạch tải", "Hủy nhiệm vụ", "Bỏ lịch DSN"], 
              "correct": 1
            },
            {
              "id": 45,
              "question": "Ops lead said scheduling gains depended on:",
              "questionVi": "Trưởng ops nói lợi ích lập lịch phụ thuộc vào:", 
              "options": ["Accurate atmospheric models, up-to-date ephemerides, dependable DSN schedules", "Pilot mood", "Launch color", "Time zone only"], 
              "optionsVi": ["Mô hình khí quyển chính xác, hiệu tinh lịch cập nhật, lịch DSN đáng tin", "Tâm trạng phi công", "Màu phóng", "Chỉ múi giờ"], 
              "correct": 0
            },
            {
              "id": 46,
              "question": "What is the 'grace buffer' policy?",
              "questionVi": "'Grace buffer' là gì?", 
              "options": ["Reserve 10% extra delta-v and 15% extra station contact time for complex rendezvous", "Cancel buffers", "Double fuel budgets always", "Only use one DSN pass"], 
              "optionsVi": ["Dự trữ 10% delta-v và 15% thời gian tiếp xúc trạm cho gặp phức tạp", "Hủy buffer", "Nhân đôi ngân sách nhiên liệu luôn", "Chỉ dùng một lượt DSN"], 
              "correct": 0
            },
            {
              "id": 47,
              "question": "A likely downstream cost of mitigation was:",
              "questionVi": "Chi phí hạ nguồn có thể của biện pháp là:", 
              "options": ["Saved propellant", "Additional propellant and replanning of payload activities", "More DSN time for free", "Shorter mission"], 
              "optionsVi": ["Tiết kiệm nhiên liệu", "Thêm nhiên liệu và lập lại kế hoạch tải", "Thêm thời gian DSN miễn phí", "Nhiệm vụ ngắn hơn"], 
              "correct": 1
            },
            {
              "id": 48,
              "question": "Author stance is best described as:",
              "questionVi": "Quan điểm tác giả mô tả thế nào là phù hợp nhất?", 
              "options": ["Operational, cautious and evidence-based", "Evangelical for risk-taking", "Promotional", "Detached fiction"], 
              "optionsVi": ["Vận hành, thận trọng và dựa trên bằng chứng", "Khuyến khích mạo hiểm", "Quảng bá", "Hư cấu tách rời"], 
              "correct": 0
            },
            {
              "id": 49,
              "question": "Inference: Monte Carlo ensemble is used to:",
              "questionVi": "Suy luận: ensemble Monte Carlo được dùng để:", 
              "options": ["Validate windows against probabilistic perturbations across 30 days", "Replace DSN passes", "Reduce delta-v budgets to zero", "Ignore ephemerides"], 
              "optionsVi": ["Xác thực cửa sổ trước biến động ngẫu nhiên trong 30 ngày", "Thay lượt DSN", "Giảm delta-v về 0", "Bỏ qua hiệu tinh lịch"], 
              "correct": 0
            },
            {
              "id": 50,
              "question": "Best summary:",
              "questionVi": "Tóm tắt tốt nhất:", 
              "options": ["Scheduling must integrate models, DSN, and fuel margins; buffers and Monte Carlo validation reduce replan risk", "Only fuel budgets matter", "DSN schedules are irrelevant", "Monte Carlo is too slow"], 
              "optionsVi": ["Lập lịch phải tích hợp mô hình, DSN và biên nhiên liệu; buffer và kiểm chứng Monte Carlo giảm rủi ro lập lại kế hoạch", "Chỉ ngân sách nhiên liệu quan trọng", "Lịch DSN không liên quan", "Monte Carlo quá chậm"], 
              "correct": 0
            }
          ]
        }
      ]
    },
    "listening": {
      "title": "Section C: Listening Comprehension — Launch Notices & Anomaly Briefs",
      "titleVi": "Phần C: Nghe hiểu — Thông báo phóng & Tóm tắt bất thường",
      "description": "10 MCQs • Dense times, hard windows, ambiguity traps (T-0, hard cutoffs, tag conventions, escalation channels)",
      "descriptionVi": "10 câu trắc nghiệm • Thời điểm dày đặc, cửa sổ cứng, bẫy mơ hồ (T-0, đóng cứng, tiêu chuẩn thẻ, kênh leo thang)",
      "totalQuestions": 10,
      "scripts": [
        {
          "id": 1,
          "title": "Script 1 – Launch Pad & Tagging Instructions",
          "titleVi": "Băng 1 – Hướng dẫn bệ phóng & Gắn thẻ",
          "content": "Launch Ops — for tonight's wet dress, label build artifacts with LAUNCH_2025-09-29_PAD_A (not _B). Mobile AIT teams begin ingress at 18:00 UTC; integrated stack roll to pad nominally 19:20. T-0 hold points at T-120 and T-15 will be enforced; hard cutoff at T-5 regardless of transfer status. If your telemetry link trails, do not resubmit on the public bucket—open a ticket to flightops@ and ping the launch bridge. Any late vendor returns must include traceability logs or they'll be quarantined and omitted from launch manifest.",
          "contentVi": "Vận hành phóng — cho buổi mặc ướt tối nay, gắn thẻ artifact: LAUNCH_2025-09-29_PAD_A (không phải _B). Đội AIT di động bắt đầu vào lúc 18:00 UTC; chuyển cấu trúc tích hợp ra bệ phóng dự kiến 19:20. Điểm dừng T-0 ở T-120 và T-15 sẽ được thực thi; đóng cứng tại T-5 bất kể trạng thái truyền. Nếu link telemetry trễ, đừng gửi lại lên bucket công cộng — mở ticket tới flightops@ và ping cầu phóng. Mọi trả lại nhà cung cấp muộn phải có nhật ký truy xuất hoặc sẽ bị cách ly và loại khỏi danh mục phóng.",
          "contentVi": "Vận hành phóng — cho buổi mặc ướt tối nay, gắn thẻ artifact: LAUNCH_2025-09-29_PAD_A (không phải _B). Đội AIT di động bắt đầu vào lúc 18:00 UTC; chuyển cấu trúc tích hợp ra bệ phóng dự kiến 19:20. Điểm dừng T-0 ở T-120 và T-15 sẽ được thực thi; đóng cứng tại T-5 bất kể trạng thái truyền. Nếu link telemetry trễ, đừng gửi lại lên bucket công cộng — mở ticket tới flightops@ và ping cầu phóng. Mọi trả lại nhà cung cấp muộn phải có nhật ký truy xuất hoặc sẽ bị cách ly và loại khỏi danh mục phóng.",
          "questions": [
            {
              "id": 51,
              "question": "Correct artifact tag:",
              "questionVi": "Thẻ artifact đúng:",
              "options": ["LAUNCH_2025-09-29_PAD_A", "LAUNCH_2025-09-29_PAD_B", "LAUNCH_2025-09-28_PAD_A", "LAUNCH_PAD_29"], 
              "optionsVi": ["LAUNCH_2025-09-29_PAD_A", "LAUNCH_2025-09-29_PAD_B", "LAUNCH_2025-09-28_PAD_A", "LAUNCH_PAD_29"], 
              "correct": 0
            },
            {
              "id": 52,
              "question": "Stack roll to pad nominal time:",
              "questionVi": "Thời gian chuyển cấu trúc ra bệ dự kiến:", 
              "options": ["18:00 UTC", "19:20 UTC", "T-120", "T-5"], 
              "optionsVi": ["18:00 UTC", "19:20 UTC", "T-120", "T-5"], 
              "correct": 1
            },
            {
              "id": 53,
              "question": "Hard cutoff at:",
              "questionVi": "Đóng cứng lúc:", 
              "options": ["T-120", "T-15", "T-5 regardless of transfer status", "T-0 only"], 
              "optionsVi": ["T-120", "T-15", "T-5 bất kể trạng thái truyền", "Chỉ T-0"], 
              "correct": 2
            },
            {
              "id": 54,
              "question": "If telemetry link trails, you should:",
              "questionVi": "Nếu link telemetry trễ, bạn nên:", 
              "options": ["Resubmit to public bucket", "Open ticket to flightops@ and ping the launch bridge", "Wait until next day", "Ignore"], 
              "optionsVi": ["Gửi lại lên bucket công cộng", "Mở ticket tới flightops@ và ping cầu phóng", "Chờ đến hôm sau", "Bỏ qua"], 
              "correct": 1
            },
            {
              "id": 55,
              "question": "Late vendor returns without trace logs will be:",
              "questionVi": "Trả lại nhà cung cấp muộn không có nhật ký truy xuất sẽ:", 
              "options": ["Fast-tracked", "Quarantined and omitted from launch manifest", "Given extra time", "Accepted without checks"], 
              "optionsVi": ["Ưu tiên nhanh", "Cách ly và loại khỏi danh mục phóng", "Cho thêm thời gian", "Chấp nhận không kiểm tra"], 
              "correct": 1
            }
          ]
        },
        {
          "id": 2,
          "title": "Script 2 – Anomaly Brief: Attitude Drift During Insertion",
          "titleVi": "Băng 2 – Tóm tắt bất thường: Trôi phương vị khi đưa vào quỹ đạo",
          "content": "Bridge — anomaly update: at 20:32 UTC, after insertion burn nominal, ops saw a slow attitude drift of 0.07 deg/min. Avionics and propulsion ran quick loops: no hardware faults flagged but a stale inertial reference frame became apparent once GF updates arrived late. Teams executed a corrective attitude trim at 20:48 and suppressed non-critical telemetry streams to preserve bandwidth. If further drift exceeds 0.12 deg/min, escalate to SEV-1 and prepare contingency spin-up of backup reaction wheels. Keep non-essential teams on standby; only core flight dynamics and avionics remain on the bridge. If your console loses bridge audio, join the incident channel and ping the anomaly lead.",
          "contentVi": "Cầu — cập nhật bất thường: lúc 20:32 UTC, sau đốt đưa quỹ đạo diễn ra bình thường, ops thấy trôi phương vị chậm 0,07 độ/phút. Avionics và hệ đẩy chạy vòng kiểm tra nhanh: không có lỗi phần cứng nhưng khung tham chiếu quán tính cũ lộ ra khi cập nhật GF đến muộn. Các đội thực hiện cắt tỉa phương vị khắc phục lúc 20:48 và ức chế các luồng telemetry không quan trọng để tiết kiệm băng thông. Nếu trôi tiếp vượt 0,12 độ/phút, leo thang thành SEV-1 và chuẩn bị quay bánh phản lực dự phòng. Giữ đội không thiết yếu ở chế độ chờ; chỉ duy trì động học bay và avionics trên cầu. Nếu console bạn mất âm thanh cầu, tham gia kênh sự cố và ping trưởng bất thường.",
          "questions": [
            {
              "id": 56,
              "question": "Initial observed drift rate:",
              "questionVi": "Tốc độ trôi ban đầu quan sát:", 
              "options": ["0.07 deg/min", "0.12 deg/min", "1 deg/min", "0 deg/min"], 
              "optionsVi": ["0.07 độ/phút", "0.12 độ/phút", "1 độ/phút", "0 độ/phút"], 
              "correct": 0
            },
            {
              "id": 57,
              "question": "Corrective action taken at 20:48:",
              "questionVi": "Biện pháp khắc phục thực hiện lúc 20:48:", 
              "options": ["Abort mission", "Attitude trim and suppress non-critical telemetry", "Spin up backup wheels immediately", "Open all telemetry channels"], 
              "optionsVi": ["Hủy nhiệm vụ", "Cắt tỉa phương vị và ức chế telemetry không quan trọng", "Quay bánh phản lực dự phòng ngay", "Mở tất cả kênh telemetry"], 
              "correct": 1
            },
            {
              "id": 58,
              "question": "Escalation threshold to SEV-1:",
              "questionVi": "Ngưỡng leo thành SEV-1:", 
              "options": ["0.05 deg/min", "0.12 deg/min", "1 deg/min", "0.07 deg/min"], 
              "optionsVi": ["0.05 độ/phút", "0.12 độ/phút", "1 độ/phút", "0.07 độ/phút"], 
              "correct": 1
            },
            {
              "id": 59,
              "question": "Which teams remain on the bridge:",
              "questionVi": "Đội nào ở lại trên cầu:", 
              "options": ["All teams", "Only core flight dynamics and avionics", "Marketing and legal", "Supply chain only"], 
              "optionsVi": ["Tất cả đội", "Chỉ động học bay và avionics", "Marketing và pháp chế", "Chỉ chuỗi cung ứng"], 
              "correct": 1
            },
            {
              "id": 60,
              "question": "If your console loses audio you should:",
              "questionVi": "Nếu console bạn mất âm thanh bạn nên:", 
              "options": ["Do nothing", "Join the incident channel and ping the anomaly lead", "Shut down your console", "Leave the bridge"], 
              "optionsVi": ["Không làm gì", "Tham gia kênh sự cố và ping trưởng bất thường", "Tắt console", "Rời cầu"], 
              "correct": 1
            }
          ]
        }
      ]
    },
    "writing": {
      "title": "Section D: Writing — Mission Scenarios & Decision-Making",
      "titleVi": "Phần D: Viết — Tình huống nhiệm vụ & Ra quyết định",
      "description": "3 tasks • Formal incident report email, opinion essay on risk-vs-velocity in mission planning, data description & recommendation with KPI and Monte Carlo trade-offs",
      "descriptionVi": "3 bài • Email báo cáo sự cố trang trọng, luận ý kiến về rủi ro-vs-tốc độ trong lập kế hoạch nhiệm vụ, mô tả dữ liệu & khuyến nghị kèm KPI và đánh đổi Monte Carlo",
      "totalTasks": 3,
      "tasks": [
        {
          "id": 1,
          "title": "Task 1 (200–240 words) — Formal Incident Email to Mission Director (Telemetry & Corrective Actions)",
          "titleVi": "Bài 1 (200–240 từ) — Email sự cố trang trọng gửi Giám đốc nhiệm vụ (Telemetry & Biện pháp khắc phục)",
          "instruction": "Write a concise incident email describing: (a) timeline of events with precise UTC timestamps for insertion burn (20:30 UTC), drift detection (20:32 UTC), corrective trim (20:48 UTC), and current status; (b) immediate mitigations taken (trim, telemetry suppression, bridge core-team only), (c) escalation criteria (drift >0.12 deg/min → SEV-1), and (d) recommended next steps including prep for backup reaction wheel spin-up and vendor traceability audit. Keep formal technical register and include exact timestamps.",
          "instructionVi": "Viết email sự cố ngắn gọn mô tả: (a) dòng thời gian với mốc UTC chính xác cho đốt đưa quỹ đạo (20:30 UTC), phát hiện trôi (20:32 UTC), cắt tỉa khắc phục (20:48 UTC) và trạng thái hiện tại; (b) biện pháp khắc phục ngay (cắt tỉa, ức chế telemetry, chỉ đội lõi trên cầu), (c) tiêu chí leo thang (trôi >0,12 độ/phút → SEV-1), và (d) bước tiếp theo đề xuất gồm chuẩn bị quay bánh phản lực dự phòng và kiểm toán truy xuất nhà cung cấp. Giữ văn phong kỹ thuật trang trọng và nêu mốc chính xác.",
          "wordLimit": { "min": 200, "max": 240 },
          "type": "formal_email",
          "topic": "telemetry_attitude_incident"
        },
        {
          "id": 2,
          "title": "Task 2 (360–420 words) — Opinion Essay (Risk vs Velocity in Mission Planning)",
          "titleVi": "Bài 2 (360–420 từ) — Bài luận ý kiến (Rủi ro vs Tốc độ trong lập kế hoạch nhiệm vụ)",
          "instruction": "“Space programs should prioritise conservative scheduling and buffer margins over aggressive mission tempo to ensure mission assurance.” To what extent do you agree? Present a clear thesis; provide one detailed case-based example (costs in propellant, schedule slip vs avoided anomaly probability), acknowledge a counter-argument (strategic tempo, competitive launch cadence, commercial pressure), and rebut it using risk quantification (expected value of mission loss vs marginal schedule gains) and operational metrics (anomaly rate, replan cost).",
          "instructionVi": "“Các chương trình không gian nên ưu tiên lịch trình thận trọng và biên dự phòng hơn tốc độ nhiệm vụ để đảm bảo đảm bảo nhiệm vụ.” Bạn đồng ý ở mức nào? Nêu luận điểm rõ; đưa ra ví dụ dựa trên trường hợp cụ thể (chi phí nhiên liệu, trượt lịch vs xác suất tránh được bất thường), thừa nhận phản biện (nhịp độ chiến lược, cadence phóng cạnh tranh, áp lực thương mại), và phản bác bằng lượng hoá rủi ro (giá trị kỳ vọng mất nhiệm vụ vs lợi ích lịch trình cận biên) và các chỉ số vận hành (tỷ lệ bất thường, chi phí lập lại kế hoạch).",
          "instructionViExtra": "Use concrete numeric comparisons where possible; show the trade-off logic clearly.",
          "wordLimit": { "min": 360, "max": 420 },
          "type": "opinion_essay",
          "topic": "risk_vs_velocity_mission_planning"
        },
        {
          "id": 3,
          "title": "Task 3 (300–340 words) — Data Description & Recommendation (Monte Carlo Buffering)",
          "titleVi": "Bài 3 (300–340 từ) — Mô tả dữ liệu & Khuyến nghị (Đệm Monte Carlo)",
          "instruction": "You are comparing two scheduling policies over a 30-day Monte Carlo ensemble for complex rendezvous: Policy A (Lean) — 0% delta-v buffer, DSN allocation minimal, median success rate 78%, median extra-propellant cost if replanned +0%; Policy B (Buffered) — 10% delta-v buffer and 15% extra station time reserved, median success rate 94%, median extra-propellant cost +6% and average schedule slip 0.8 days. Summarise trade-offs (success vs cost vs schedule), recommend a policy for an operator with limited propellant margin but high contractual penalties for missed rendezvous, and state one KPI to monitor weekly (e.g., 'simulated success probability with 95% CI'). Include brief Monte Carlo interpretation (what median and CI mean here).",
          "instructionVi": "Bạn so sánh hai chính sách lập lịch qua ensemble Monte Carlo 30 ngày cho gặp phức tạp: A (Lean) — 0% delta-v buffer, DSN tối thiểu, tỉ lệ thành công trung vị 78%, chi phí nhiên liệu bổ sung trung vị nếu lập lại +0%; B (Buffered) — 10% delta-v buffer và 15% thời gian trạm dự phòng, tỉ lệ thành công trung vị 94%, chi phí nhiên liệu bổ sung trung vị +6% và trượt lịch trung bình 0,8 ngày. Tóm tắt đánh đổi (thành công vs chi phí vs lịch), đề xuất chính sách cho nhà điều hành có biên nhiên liệu hạn chế nhưng phạt hợp đồng cao khi lỡ gặp, và nêu KPI theo dõi hàng tuần (ví dụ 'xác suất thành công mô phỏng với CI 95%'). Bao gồm giải thích ngắn về Monte Carlo (median và CI là gì ở đây).",
          "wordLimit": { "min": 300, "max": 340 },
          "type": "data_description",
          "topic": "monte_carlo_buffer_tradeoffs",
          "chartData": {
            "title": "Monte Carlo — Lean vs Buffered Rendezvous Policies",
            "titleVi": "Monte Carlo — Chính sách gặp Lean vs Buffered",
            "data": [
              { "policy": "Lean", "delta_v_buffer_percent": 0, "dsN_alloc": "minimal", "median_success_rate_percent": 78, "median_extra_propellant_percent": 0, "avg_schedule_slip_days": 0.0 },
              { "policy": "Buffered", "delta_v_buffer_percent": 10, "dsN_alloc": "reserved+15%", "median_success_rate_percent": 94, "median_extra_propellant_percent": 6, "avg_schedule_slip_days": 0.8 }
            ]
          }
        }
      ]
    }
  },
  "metadata": {
    "createdBy": "IELTS Practice System",
    "version": "3.9.0",
    "lastUpdated": "2025-09-29",
    "difficulty": "advanced (3.9) — dense technical reading and inference required",
    "estimatedTime": "130–160 minutes",
    "tags": [
      "ielts",
      "space",
      "mission-ops",
      "telemetry",
      "rendezvous",
      "AIT",
      "HITL",
      "delta-v",
      "monte-carlo",
      "contamination-control",
      "grammar",
      "reading",
      "listening",
      "writing",
      "bilingual",
      "high-density"
    ]
  }
}
